<annotation>
	<folder>jpg versions</folder>
	<filename>DSC_0037_00018.jpg</filename>
	<path>Z:\luke9\Project work\jpg versions\DSC_0037_00018.jpg</path>
	<source>
		<database>Unknown</database>
	</source>
	<size>
		<width>6016</width>
		<height>4000</height>
		<depth>3</depth>
	</size>
	<segmented>0</segmented>
	<object>
		<name>resistor</name>
		<pose>Unspecified</pose>
		<truncated>0</truncated>
		<difficult>0</difficult>
		<bndbox>
			<xmin>2834</xmin>
			<ymin>977</ymin>
			<xmax>3616</xmax>
			<ymax>1804</ymax>
		</bndbox>
	</object>
	<object>
		<name>resistor</name>
		<pose>Unspecified</pose>
		<truncated>0</truncated>
		<difficult>0</difficult>
		<bndbox>
			<xmin>1943</xmin>
			<ymin>2222</ymin>
			<xmax>2707</xmax>
			<ymax>3013</ymax>
		</bndbox>
	</object>
	<object>
		<name>resistor</name>
		<pose>Unspecified</pose>
		<truncated>0</truncated>
		<difficult>0</difficult>
		<bndbox>
			<xmin>4562</xmin>
			<ymin>2140</ymin>
			<xmax>5043</xmax>
			<ymax>2895</ymax>
		</bndbox>
	</object>
	<object>
		<name>resistor</name>
		<pose>Unspecified</pose>
		<truncated>0</truncated>
		<difficult>0</difficult>
		<bndbox>
			<xmin>4016</xmin>
			<ymin>2958</ymin>
			<xmax>4789</xmax>
			<ymax>3731</ymax>
		</bndbox>
	</object>
	<object>
		<name>resistor</name>
		<pose>Unspecified</pose>
		<truncated>0</truncated>
		<difficult>0</difficult>
		<bndbox>
			<xmin>4953</xmin>
			<ymin>2749</ymin>
			<xmax>5580</xmax>
			<ymax>3413</ymax>
		</bndbox>
	</object>
	<object>
		<name>resistor</name>
		<pose>Unspecified</pose>
		<truncated>1</truncated>
		<difficult>0</difficult>
		<bndbox>
			<xmin>4998</xmin>
			<ymin>3486</ymin>
			<xmax>5670</xmax>
			<ymax>4000</ymax>
		</bndbox>
	</object>
	<object>
		<name>resistor</name>
		<pose>Unspecified</pose>
		<truncated>1</truncated>
		<difficult>0</difficult>
		<bndbox>
			<xmin>5653</xmin>
			<ymin>3186</ymin>
			<xmax>6016</xmax>
			<ymax>3859</ymax>
		</bndbox>
	</object>
</annotation>
